<order>
<merchantId>np_peqob826806</merchantId>
<certiKey>1A40C774-07A8-415C-998C-F001B9F89873</certiKey>
<product>
<id>1000000034</id>
<ecMallProductId>1000000034</ecMallProductId>
<name><![CDATA[[생활지음] 루미(LUMI) 4LEGS(WOOD) SSLM34W /로즈핑크_RP]]></name>
<basePrice>45600</basePrice>
<taxType>TAX</taxType>
<infoUrl><![CDATA[https://ziummall.com:443/goods/goods_view.php?inflow=naverPay&goodsNo=1000000034]]></infoUrl>
<imageUrl><![CDATA[http://ziummall.com/data/goods/18/06/26/1000000034/1000000034_main_083.jpg]]></imageUrl>
<shippingPolicy>
<groupId>5_0</groupId>
<method>DELIVERY</method>
<chargeByQuantity>
<type>REPEAT</type>
<repeatQuantity>2</repeatQuantity>
</chargeByQuantity>
<feePayType>PREPAYED</feePayType>
<feePrice>5500</feePrice>
<feeType>CHARGE_BY_QUANTITY</feeType>
<surchargeByArea>
<splitUnit>2</splitUnit>
<area2Price>10000</area2Price>
</surchargeByArea>
</shippingPolicy><option>
<quantity>1</quantity>
<selectedItem>
<type>SELECT</type>
<name><![CDATA[색상]]></name>
<value>
<id>S_2edd50e7168c8f339b516d7d542bd0</id>
<text><![CDATA[로즈핑크(RP)]]></text>
</value>
</selectedItem>
<manageCode>option39</manageCode>
<price>0</price>
</option>

</product>
<backUrl><![CDATA[https://ziummall.com:443/goods/goods_view.php?inflow=naverPay&goodsNo=1000000034]]></backUrl>
<interface>
<salesCode></salesCode>
<cpaInflowCode></cpaInflowCode>
<mileageInflowCode></mileageInflowCode>
<naverInflowCode>ct=jj9jfnke|ci=checkout|tr=myz|hk=730b5def2efca089bc4c57874cf9f7512ae83183|trx=</naverInflowCode>
<saClickId></saClickId>
<merchantCustomCode1>1807061435247240</merchantCustomCode1>
</interface>
</order
